<?xml version="1.0" encoding="UTF-8" standalone="yes"?>
<w:document xmlns:wpc="http://schemas.microsoft.com/office/word/2010/wordprocessingCanvas" xmlns:cx="http://schemas.microsoft.com/office/drawing/2014/chartex" xmlns:cx1="http://schemas.microsoft.com/office/drawing/2015/9/8/chartex" xmlns:cx2="http://schemas.microsoft.com/office/drawing/2015/10/21/chartex" xmlns:cx3="http://schemas.microsoft.com/office/drawing/2016/5/9/chartex" xmlns:cx4="http://schemas.microsoft.com/office/drawing/2016/5/10/chartex" xmlns:cx5="http://schemas.microsoft.com/office/drawing/2016/5/11/chartex" xmlns:cx6="http://schemas.microsoft.com/office/drawing/2016/5/12/chartex" xmlns:cx7="http://schemas.microsoft.com/office/drawing/2016/5/13/chartex" xmlns:cx8="http://schemas.microsoft.com/office/drawing/2016/5/14/chartex" xmlns:mc="http://schemas.openxmlformats.org/markup-compatibility/2006" xmlns:aink="http://schemas.microsoft.com/office/drawing/2016/ink" xmlns:am3d="http://schemas.microsoft.com/office/drawing/2017/model3d" xmlns:o="urn:schemas-microsoft-com:office:office" xmlns:oel="http://schemas.microsoft.com/office/2019/extlst" xmlns:r="http://schemas.openxmlformats.org/officeDocument/2006/relationships" xmlns:m="http://schemas.openxmlformats.org/officeDocument/2006/math" xmlns:v="urn:schemas-microsoft-com:vml" xmlns:wp14="http://schemas.microsoft.com/office/word/2010/wordprocessingDrawing" xmlns:wp="http://schemas.openxmlformats.org/drawingml/2006/wordprocessingDrawing" xmlns:w10="urn:schemas-microsoft-com:office:word" xmlns:w="http://schemas.openxmlformats.org/wordprocessingml/2006/main" xmlns:w14="http://schemas.microsoft.com/office/word/2010/wordml" xmlns:w15="http://schemas.microsoft.com/office/word/2012/wordml" xmlns:w16cex="http://schemas.microsoft.com/office/word/2018/wordml/cex" xmlns:w16cid="http://schemas.microsoft.com/office/word/2016/wordml/cid" xmlns:w16="http://schemas.microsoft.com/office/word/2018/wordml" xmlns:w16sdtdh="http://schemas.microsoft.com/office/word/2020/wordml/sdtdatahash" xmlns:w16se="http://schemas.microsoft.com/office/word/2015/wordml/symex" xmlns:wpg="http://schemas.microsoft.com/office/word/2010/wordprocessingGroup" xmlns:wpi="http://schemas.microsoft.com/office/word/2010/wordprocessingInk" xmlns:wne="http://schemas.microsoft.com/office/word/2006/wordml" xmlns:wps="http://schemas.microsoft.com/office/word/2010/wordprocessingShape" mc:Ignorable="w14 w15 w16se w16cid w16 w16cex w16sdtdh wp14"><w:body><w:p w14:paraId="52D947D5" w14:textId="77777777" w:rsidR="00681D42" w:rsidRPr="003D3A05" w:rsidRDefault="00681D42" w:rsidP="003D3A05"><w:pPr><w:pStyle w:val="CorpsA"/><w:jc w:val="center"/><w:rPr><w:rFonts w:ascii="Calibri" w:hAnsi="Calibri" w:cs="Calibri"/><w:sz w:val="22"/><w:szCs w:val="22"/><w:lang w:val="en-US"/></w:rPr></w:pPr></w:p><w:p w14:paraId="6C055E17" w14:textId="26483A63" w:rsidR="00980D59" w:rsidRPr="007F02C9" w:rsidRDefault="00681D42" w:rsidP="003D3A05"><w:pPr><w:pStyle w:val="CorpsA"/><w:jc w:val="center"/><w:rPr><w:rFonts w:ascii="Calibri" w:hAnsi="Calibri" w:cs="Calibri"/><w:b/><w:bCs/><w:lang w:val="en-US"/></w:rPr></w:pPr><w:r w:rsidRPr="007F02C9"><w:rPr><w:rFonts w:ascii="Calibri" w:hAnsi="Calibri" w:cs="Calibri"/><w:b/><w:bCs/><w:lang w:val="en-US"/></w:rPr><w:t xml:space="preserve">ERROR </w:t></w:r><w:r w:rsidR="00443651"><w:rPr><w:rFonts w:ascii="Calibri" w:hAnsi="Calibri" w:cs="Calibri"/><w:b/><w:bCs/><w:lang w:val="en-US"/></w:rPr><w:t>CRC</w:t></w:r><w:r w:rsidR="00B22118"><w:rPr><w:rFonts w:ascii="Calibri" w:hAnsi="Calibri" w:cs="Calibri"/><w:b/><w:bCs/><w:lang w:val="en-US"/></w:rPr><w:t xml:space="preserve"> </w:t></w:r><w:r w:rsidR="00443651"><w:rPr><w:rFonts w:ascii="Calibri" w:hAnsi="Calibri" w:cs="Calibri"/><w:b/><w:bCs/><w:lang w:val="en-US"/></w:rPr><w:t>FILE</w:t></w:r></w:p><w:p w14:paraId="5D8B94DD" w14:textId="77777777" w:rsidR="00093581" w:rsidRDefault="00093581" w:rsidP="003D3A05"><w:pPr><w:pStyle w:val="CorpsA"/><w:jc w:val="both"/><w:rPr><w:rFonts w:ascii="Calibri" w:hAnsi="Calibri" w:cs="Calibri"/><w:sz w:val="22"/><w:szCs w:val="22"/><w:lang w:val="en-US"/></w:rPr></w:pPr></w:p><w:p w14:paraId="58F32236" w14:textId="254614A4" w:rsidR="003D3A05" w:rsidRDefault="003D3A05" w:rsidP="003D3A05"><w:pPr><w:pStyle w:val="CorpsA"/><w:jc w:val="both"/><w:rPr><w:rFonts w:ascii="Calibri" w:hAnsi="Calibri" w:cs="Calibri"/><w:b/><w:bCs/><w:sz w:val="22"/><w:szCs w:val="22"/><w:lang w:val="en-US"/></w:rPr></w:pPr><w:r w:rsidRPr="003D3A05"><w:rPr><w:rFonts w:ascii="Calibri" w:hAnsi="Calibri" w:cs="Calibri"/><w:b/><w:bCs/><w:sz w:val="22"/><w:szCs w:val="22"/><w:lang w:val="en-US"/></w:rPr><w:t>Description</w:t></w:r></w:p><w:p w14:paraId="6D15A7F2" w14:textId="77777777" w:rsidR="00DB6004" w:rsidRPr="003D3A05" w:rsidRDefault="00DB6004" w:rsidP="003D3A05"><w:pPr><w:pStyle w:val="CorpsA"/><w:jc w:val="both"/><w:rPr><w:rFonts w:ascii="Calibri" w:hAnsi="Calibri" w:cs="Calibri"/><w:b/><w:bCs/><w:sz w:val="22"/><w:szCs w:val="22"/><w:lang w:val="en-US"/></w:rPr></w:pPr></w:p><w:p w14:paraId="1BAFB752" w14:textId="326342DC" w:rsidR="003D3A05" w:rsidRDefault="00443651" w:rsidP="003D3A05"><w:pPr><w:pStyle w:val="CorpsA"/><w:jc w:val="both"/><w:rPr><w:rFonts w:ascii="Calibri" w:hAnsi="Calibri" w:cs="Calibri"/><w:color w:val="auto"/><w:sz w:val="22"/><w:szCs w:val="22"/><w:lang w:val="en-US"/></w:rPr></w:pPr><w:r><w:rPr><w:rFonts w:ascii="Calibri" w:hAnsi="Calibri" w:cs="Calibri"/><w:sz w:val="22"/><w:szCs w:val="22"/><w:lang w:val="en-US"/></w:rPr><w:t xml:space="preserve">The screen with the message </w:t></w:r><w:r w:rsidR="002D2A75" w:rsidRPr="002D2A75"><w:rPr><w:rFonts w:ascii="Calibri" w:hAnsi="Calibri" w:cs="Calibri"/><w:sz w:val="22"/><w:szCs w:val="22"/><w:lang w:val="en-US"/></w:rPr><w:t>"</w:t></w:r><w:r w:rsidR="00A67009" w:rsidRPr="00A67009"><w:rPr><w:rFonts w:ascii="Calibri" w:hAnsi="Calibri" w:cs="Calibri"/><w:sz w:val="22"/><w:szCs w:val="22"/><w:lang w:val="en-US"/></w:rPr><w:t>ERROR</w:t></w:r><w:r><w:rPr><w:rFonts w:ascii="Calibri" w:hAnsi="Calibri" w:cs="Calibri"/><w:sz w:val="22"/><w:szCs w:val="22"/><w:lang w:val="en-US"/></w:rPr><w:t xml:space="preserve"> CRC FILE v</w:t></w:r><w:r w:rsidR="00DB6004"><w:rPr><w:rFonts w:ascii="Calibri" w:hAnsi="Calibri" w:cs="Calibri"/><w:color w:val="EA8300" w:themeColor="accent4" w:themeShade="BF"/><w:sz w:val="22"/><w:szCs w:val="22"/><w:lang w:val="en-US"/></w:rPr><w:t>*</w:t></w:r><w:r><w:rPr><w:rFonts w:ascii="Calibri" w:hAnsi="Calibri" w:cs="Calibri"/><w:color w:val="EA8300" w:themeColor="accent4" w:themeShade="BF"/><w:sz w:val="22"/><w:szCs w:val="22"/><w:lang w:val="en-US"/></w:rPr><w:t>.</w:t></w:r><w:r w:rsidR="00DB6004"><w:rPr><w:rFonts w:ascii="Calibri" w:hAnsi="Calibri" w:cs="Calibri"/><w:color w:val="EA8300" w:themeColor="accent4" w:themeShade="BF"/><w:sz w:val="22"/><w:szCs w:val="22"/><w:lang w:val="en-US"/></w:rPr><w:t>**</w:t></w:r><w:r w:rsidR="00FB008A"><w:rPr><w:rFonts w:ascii="Calibri" w:hAnsi="Calibri" w:cs="Calibri"/><w:sz w:val="22"/><w:szCs w:val="22"/><w:lang w:val="en-US"/></w:rPr><w:t>” appeared on the screen (</w:t></w:r><w:r w:rsidR="00DB6004"><w:rPr><w:rFonts w:ascii="Calibri" w:hAnsi="Calibri" w:cs="Calibri"/><w:color w:val="EA8300" w:themeColor="accent4" w:themeShade="BF"/><w:sz w:val="22"/><w:szCs w:val="22"/><w:lang w:val="en-US"/></w:rPr><w:t>*</w:t></w:r><w:r w:rsidR="00FB008A"><w:rPr><w:rFonts w:ascii="Calibri" w:hAnsi="Calibri" w:cs="Calibri"/><w:color w:val="auto"/><w:sz w:val="22"/><w:szCs w:val="22"/><w:lang w:val="en-US"/></w:rPr><w:t xml:space="preserve"> = </w:t></w:r><w:r><w:rPr><w:rFonts w:ascii="Calibri" w:hAnsi="Calibri" w:cs="Calibri"/><w:color w:val="auto"/><w:sz w:val="22"/><w:szCs w:val="22"/><w:lang w:val="en-US"/></w:rPr><w:t>version</w:t></w:r><w:r w:rsidR="00DB6004"><w:rPr><w:rFonts w:ascii="Calibri" w:hAnsi="Calibri" w:cs="Calibri"/><w:color w:val="auto"/><w:sz w:val="22"/><w:szCs w:val="22"/><w:lang w:val="en-US"/></w:rPr><w:t xml:space="preserve"> and revision</w:t></w:r><w:r><w:rPr><w:rFonts w:ascii="Calibri" w:hAnsi="Calibri" w:cs="Calibri"/><w:color w:val="auto"/><w:sz w:val="22"/><w:szCs w:val="22"/><w:lang w:val="en-US"/></w:rPr><w:t xml:space="preserve"> number</w:t></w:r><w:r w:rsidR="00FB008A"><w:rPr><w:rFonts w:ascii="Calibri" w:hAnsi="Calibri" w:cs="Calibri"/><w:color w:val="auto"/><w:sz w:val="22"/><w:szCs w:val="22"/><w:lang w:val="en-US"/></w:rPr><w:t>).</w:t></w:r></w:p><w:p w14:paraId="2027DA87" w14:textId="77777777" w:rsidR="00712461" w:rsidRDefault="00712461" w:rsidP="003D3A05"><w:pPr><w:pStyle w:val="CorpsA"/><w:jc w:val="both"/><w:rPr><w:rFonts w:ascii="Calibri" w:hAnsi="Calibri" w:cs="Calibri"/><w:color w:val="auto"/><w:sz w:val="22"/><w:szCs w:val="22"/><w:lang w:val="en-US"/></w:rPr></w:pPr></w:p><w:p w14:paraId="2C900A01" w14:textId="2CDC97B7" w:rsidR="00712461" w:rsidRDefault="00712461" w:rsidP="00712461"><w:pPr><w:pStyle w:val="CorpsA"/><w:jc w:val="center"/><w:rPr><w:rFonts w:ascii="Calibri" w:hAnsi="Calibri" w:cs="Calibri"/><w:sz w:val="22"/><w:szCs w:val="22"/><w:lang w:val="en-US"/></w:rPr></w:pPr><w:r><w:rPr><w:noProof/></w:rPr><w:drawing><wp:inline distT="0" distB="0" distL="0" distR="0" wp14:anchorId="25B508AC" wp14:editId="2D1A6303"><wp:extent cx="2377078" cy="2160000"/><wp:effectExtent l="0" t="0" r="4445" b="0"/><wp:docPr id="22" name="Image 22" descr="Une image contenant texte, écran, Appareils électroniques, affichage&#xA;&#xA;Description générée automatiquement"/><wp:cNvGraphicFramePr><a:graphicFrameLocks xmlns:a="http://schemas.openxmlformats.org/drawingml/2006/main" noChangeAspect="1"/></wp:cNvGraphicFramePr><a:graphic xmlns:a="http://schemas.openxmlformats.org/drawingml/2006/main"><a:graphicData uri="http://schemas.openxmlformats.org/drawingml/2006/picture"><pic:pic xmlns:pic="http://schemas.openxmlformats.org/drawingml/2006/picture"><pic:nvPicPr><pic:cNvPr id="22" name="Image 22" descr="Une image contenant texte, écran, Appareils électroniques, affichage&#xA;&#xA;Description générée automatiquement"/><pic:cNvPicPr><a:picLocks noChangeAspect="1" noChangeArrowheads="1"/></pic:cNvPicPr></pic:nvPicPr><pic:blipFill rotWithShape="1"><a:blip r:embed="rId9" cstate="print"><a:extLst><a:ext uri="{28A0092B-C50C-407E-A947-70E740481C1C}"><a14:useLocalDpi xmlns:a14="http://schemas.microsoft.com/office/drawing/2010/main" val="0"/></a:ext></a:extLst></a:blip><a:srcRect t="9956" b="21892"/><a:stretch/></pic:blipFill><pic:spPr bwMode="auto"><a:xfrm><a:off x="0" y="0"/><a:ext cx="2377078" cy="2160000"/></a:xfrm><a:prstGeom prst="rect"><a:avLst/></a:prstGeom><a:noFill/><a:ln><a:noFill/></a:ln><a:extLst><a:ext uri="{53640926-AAD7-44D8-BBD7-CCE9431645EC}"><a14:shadowObscured xmlns:a14="http://schemas.microsoft.com/office/drawing/2010/main"/></a:ext></a:extLst></pic:spPr></pic:pic></a:graphicData></a:graphic></wp:inline></w:drawing></w:r></w:p><w:p w14:paraId="21193C65" w14:textId="77777777" w:rsidR="003D3A05" w:rsidRDefault="003D3A05" w:rsidP="003D3A05"><w:pPr><w:pStyle w:val="CorpsA"/><w:jc w:val="both"/><w:rPr><w:rFonts w:ascii="Calibri" w:hAnsi="Calibri" w:cs="Calibri"/><w:sz w:val="22"/><w:szCs w:val="22"/><w:lang w:val="en-US"/></w:rPr></w:pPr></w:p><w:p w14:paraId="7BA51409" w14:textId="2508CCD0" w:rsidR="003D3A05" w:rsidRDefault="003D3A05" w:rsidP="003D3A05"><w:pPr><w:pStyle w:val="CorpsA"/><w:jc w:val="both"/><w:rPr><w:rFonts w:ascii="Calibri" w:hAnsi="Calibri" w:cs="Calibri"/><w:b/><w:bCs/><w:sz w:val="22"/><w:szCs w:val="22"/><w:lang w:val="en-US"/></w:rPr></w:pPr><w:r w:rsidRPr="003D3A05"><w:rPr><w:rFonts w:ascii="Calibri" w:hAnsi="Calibri" w:cs="Calibri"/><w:b/><w:bCs/><w:sz w:val="22"/><w:szCs w:val="22"/><w:lang w:val="en-US"/></w:rPr><w:t>Analysis</w:t></w:r></w:p><w:p w14:paraId="45824A73" w14:textId="77777777" w:rsidR="00DB6004" w:rsidRPr="003D3A05" w:rsidRDefault="00DB6004" w:rsidP="003D3A05"><w:pPr><w:pStyle w:val="CorpsA"/><w:jc w:val="both"/><w:rPr><w:rFonts w:ascii="Calibri" w:hAnsi="Calibri" w:cs="Calibri"/><w:b/><w:bCs/><w:sz w:val="22"/><w:szCs w:val="22"/><w:lang w:val="en-US"/></w:rPr></w:pPr></w:p><w:p w14:paraId="78B34B4F" w14:textId="50366EC4" w:rsidR="003D3A05" w:rsidRDefault="00443651" w:rsidP="00DB6004"><w:pPr><w:pStyle w:val="CorpsA"/><w:numPr><w:ilvl w:val="0"/><w:numId w:val="4"/></w:numPr><w:jc w:val="both"/><w:rPr><w:rFonts w:ascii="Calibri" w:hAnsi="Calibri" w:cs="Calibri"/><w:sz w:val="22"/><w:szCs w:val="22"/><w:lang w:val="en-US"/></w:rPr></w:pPr><w:r w:rsidRPr="00443651"><w:rPr><w:rFonts w:ascii="Calibri" w:hAnsi="Calibri" w:cs="Calibri"/><w:sz w:val="22"/><w:szCs w:val="22"/><w:lang w:val="en-US"/></w:rPr><w:t>This error occurs during t</w:t></w:r><w:r><w:rPr><w:rFonts w:ascii="Calibri" w:hAnsi="Calibri" w:cs="Calibri"/><w:sz w:val="22"/><w:szCs w:val="22"/><w:lang w:val="en-US"/></w:rPr><w:t>he installation of a new version. A file during the download has been corrupted.</w:t></w:r></w:p><w:p w14:paraId="3FEEB46C" w14:textId="77777777" w:rsidR="00443651" w:rsidRPr="00443651" w:rsidRDefault="00443651" w:rsidP="003D3A05"><w:pPr><w:pStyle w:val="CorpsA"/><w:jc w:val="both"/><w:rPr><w:rFonts w:ascii="Calibri" w:hAnsi="Calibri" w:cs="Calibri"/><w:sz w:val="22"/><w:szCs w:val="22"/><w:lang w:val="en-US"/></w:rPr></w:pPr></w:p><w:p w14:paraId="39A2A1BD" w14:textId="6E96C5BC" w:rsidR="003D3A05" w:rsidRDefault="0061337C" w:rsidP="003D3A05"><w:pPr><w:pStyle w:val="CorpsA"/><w:jc w:val="both"/><w:rPr><w:rFonts w:ascii="Calibri" w:hAnsi="Calibri" w:cs="Calibri"/><w:b/><w:bCs/><w:sz w:val="22"/><w:szCs w:val="22"/><w:lang w:val="en-US"/></w:rPr></w:pPr><w:r><w:rPr><w:rFonts w:ascii="Calibri" w:hAnsi="Calibri" w:cs="Calibri"/><w:b/><w:bCs/><w:sz w:val="22"/><w:szCs w:val="22"/><w:lang w:val="en-US"/></w:rPr><w:t>Repair</w:t></w:r></w:p><w:p w14:paraId="1345753A" w14:textId="77777777" w:rsidR="00DB6004" w:rsidRPr="00DB6004" w:rsidRDefault="00DB6004" w:rsidP="003D3A05"><w:pPr><w:pStyle w:val="CorpsA"/><w:jc w:val="both"/><w:rPr><w:rFonts w:ascii="Calibri" w:hAnsi="Calibri" w:cs="Calibri"/><w:b/><w:bCs/><w:sz w:val="22"/><w:szCs w:val="22"/><w:lang w:val="en-US"/></w:rPr></w:pPr></w:p><w:p w14:paraId="57ED779A" w14:textId="170B3284" w:rsidR="00AE0D83" w:rsidRPr="00443651" w:rsidRDefault="00443651" w:rsidP="00962DB2"><w:pPr><w:pStyle w:val="CorpsA"/><w:numPr><w:ilvl w:val="0"/><w:numId w:val="5"/></w:numPr><w:jc w:val="both"/><w:rPr><w:rFonts w:ascii="Calibri" w:hAnsi="Calibri" w:cs="Calibri"/><w:sz w:val="22"/><w:szCs w:val="22"/><w:lang w:val="en-US"/></w:rPr></w:pPr><w:r w:rsidRPr="00443651"><w:rPr><w:rFonts w:ascii="Calibri" w:hAnsi="Calibri" w:cs="Calibri"/><w:sz w:val="22"/><w:szCs w:val="22"/><w:lang w:val="en-US"/></w:rPr><w:t>Download the version again b</w:t></w:r><w:r><w:rPr><w:rFonts w:ascii="Calibri" w:hAnsi="Calibri" w:cs="Calibri"/><w:sz w:val="22"/><w:szCs w:val="22"/><w:lang w:val="en-US"/></w:rPr><w:t>y forcing the version into the device via the server interface.</w:t></w:r></w:p><w:p w14:paraId="7B55B9B0" w14:textId="77777777" w:rsidR="00443651" w:rsidRPr="00443651" w:rsidRDefault="00443651" w:rsidP="003D3A05"><w:pPr><w:pStyle w:val="CorpsA"/><w:jc w:val="both"/><w:rPr><w:rFonts w:ascii="Calibri" w:hAnsi="Calibri" w:cs="Calibri"/><w:sz w:val="22"/><w:szCs w:val="22"/><w:lang w:val="en-US"/></w:rPr></w:pPr></w:p><w:p w14:paraId="15FAE322" w14:textId="744C89DD" w:rsidR="00AE0D83" w:rsidRDefault="00AE0D83" w:rsidP="003D3A05"><w:pPr><w:pStyle w:val="CorpsA"/><w:jc w:val="both"/><w:rPr><w:rFonts w:ascii="Calibri" w:hAnsi="Calibri" w:cs="Calibri"/><w:sz w:val="22"/><w:szCs w:val="22"/><w:lang w:val="en-US"/></w:rPr></w:pPr><w:r w:rsidRPr="00AE0D83"><w:rPr><w:rFonts w:ascii="Calibri" w:hAnsi="Calibri" w:cs="Calibri"/><w:b/><w:bCs/><w:sz w:val="22"/><w:szCs w:val="22"/><w:lang w:val="en-US"/></w:rPr><w:t>Keywords:</w:t></w:r><w:r><w:rPr><w:rFonts w:ascii="Calibri" w:hAnsi="Calibri" w:cs="Calibri"/><w:sz w:val="22"/><w:szCs w:val="22"/><w:lang w:val="en-US"/></w:rPr><w:t xml:space="preserve"> Error / </w:t></w:r><w:r w:rsidR="00443651"><w:rPr><w:rFonts w:ascii="Calibri" w:hAnsi="Calibri" w:cs="Calibri"/><w:sz w:val="22"/><w:szCs w:val="22"/><w:lang w:val="en-US"/></w:rPr><w:t>CRC</w:t></w:r><w:r><w:rPr><w:rFonts w:ascii="Calibri" w:hAnsi="Calibri" w:cs="Calibri"/><w:sz w:val="22"/><w:szCs w:val="22"/><w:lang w:val="en-US"/></w:rPr><w:t xml:space="preserve"> /</w:t></w:r><w:r w:rsidR="00BB5FF5"><w:rPr><w:rFonts w:ascii="Calibri" w:hAnsi="Calibri" w:cs="Calibri"/><w:sz w:val="22"/><w:szCs w:val="22"/><w:lang w:val="en-US"/></w:rPr><w:t xml:space="preserve"> </w:t></w:r><w:r w:rsidR="00443651"><w:rPr><w:rFonts w:ascii="Calibri" w:hAnsi="Calibri" w:cs="Calibri"/><w:sz w:val="22"/><w:szCs w:val="22"/><w:lang w:val="en-US"/></w:rPr><w:t>File</w:t></w:r></w:p><w:p w14:paraId="72FDB2CC" w14:textId="77777777" w:rsidR="00AE0D83" w:rsidRDefault="00AE0D83" w:rsidP="003D3A05"><w:pPr><w:pStyle w:val="CorpsA"/><w:jc w:val="both"/><w:rPr><w:rFonts w:ascii="Calibri" w:hAnsi="Calibri" w:cs="Calibri"/><w:sz w:val="22"/><w:szCs w:val="22"/><w:lang w:val="en-US"/></w:rPr></w:pPr></w:p><w:p w14:paraId="5267DB16" w14:textId="6914339A" w:rsidR="00AE0D83" w:rsidRPr="00AE0D83" w:rsidRDefault="00AE0D83" w:rsidP="003D3A05"><w:pPr><w:pStyle w:val="CorpsA"/><w:jc w:val="both"/><w:rPr><w:rFonts w:ascii="Calibri" w:hAnsi="Calibri" w:cs="Calibri"/><w:b/><w:bCs/><w:sz w:val="22"/><w:szCs w:val="22"/><w:lang w:val="en-US"/></w:rPr></w:pPr><w:r w:rsidRPr="00AE0D83"><w:rPr><w:rFonts w:ascii="Calibri" w:hAnsi="Calibri" w:cs="Calibri"/><w:b/><w:bCs/><w:sz w:val="22"/><w:szCs w:val="22"/><w:lang w:val="en-US"/></w:rPr><w:t>Filters:</w:t></w:r></w:p><w:p w14:paraId="484A2241" w14:textId="3BA76B8D" w:rsidR="00961FE5" w:rsidRDefault="00CF7E58" w:rsidP="00961FE5"><w:pPr><w:pStyle w:val="CorpsA"/><w:numPr><w:ilvl w:val="0"/><w:numId w:val="3"/></w:numPr><w:jc w:val="both"/><w:rPr><w:rFonts w:ascii="Calibri" w:hAnsi="Calibri" w:cs="Calibri"/><w:sz w:val="22"/><w:szCs w:val="22"/><w:lang w:val="en-US"/></w:rPr></w:pPr><w:r><w:rPr><w:rFonts w:ascii="Calibri" w:hAnsi="Calibri" w:cs="Calibri"/><w:sz w:val="22"/><w:szCs w:val="22"/><w:lang w:val="en-US"/></w:rPr><w:t>Back2 / Back4</w:t></w:r></w:p><w:p w14:paraId="76719A00" w14:textId="357EE245" w:rsidR="00A91092" w:rsidRPr="003D3A05" w:rsidRDefault="00A91092" w:rsidP="004E7AE0"><w:pPr><w:pStyle w:val="CorpsA"/><w:jc w:val="both"/><w:rPr><w:rFonts w:ascii="Calibri" w:hAnsi="Calibri" w:cs="Calibri"/><w:sz w:val="22"/><w:szCs w:val="22"/><w:lang w:val="en-US"/></w:rPr></w:pPr></w:p><w:p w14:paraId="467CC3DB" w14:textId="4B5C426E" w:rsidR="00AE0D83" w:rsidRPr="003D3A05" w:rsidRDefault="00AE0D83" w:rsidP="00961FE5"><w:pPr><w:pStyle w:val="CorpsA"/><w:ind w:left="720"/><w:jc w:val="both"/><w:rPr><w:rFonts w:ascii="Calibri" w:hAnsi="Calibri" w:cs="Calibri"/><w:sz w:val="22"/><w:szCs w:val="22"/><w:lang w:val="en-US"/></w:rPr></w:pPr></w:p><w:sectPr w:rsidR="00AE0D83" w:rsidRPr="003D3A05" w:rsidSect="003A254A"><w:headerReference w:type="default" r:id="rId10"/><w:footerReference w:type="default" r:id="rId11"/><w:pgSz w:w="11900" w:h="16840"/><w:pgMar w:top="1440" w:right="896" w:bottom="1417" w:left="896" w:header="1020" w:footer="708" w:gutter="0"/><w:cols w:space="720"/><w:docGrid w:linePitch="326"/></w:sectPr></w:body></w:document>